{
  "kind": "collectionType",
  "collectionName": "process_steps",
  "info": {
    "singularName": "process-step",
    "pluralName": "process-steps",
    "displayName": "Process Step",
    "description": "The how-it-works steps shown on the homepage"
  },
  "options": {
    "draftAndPublish": false
  },
  "pluginOptions": {},
  "attributes": {
    "stepNumber": {
      "type": "integer",
      "required": true
    },
    "title": {
      "type": "string",
      "required": true
    },
    "description": {
      "type": "text",
      "required": true
    }
  }
}
